sag_py_fastapi_health/__init__.py
sag_py_fastapi_health/formatter.py
sag_py_fastapi_health/models.py
sag_py_fastapi_health/py.typed
sag_py_fastapi_health/router.py
sag_py_fastapi_health/checks/__init__.py
sag_py_fastapi_health/checks/http.py
sag_py_fastapi_health/checks/py.typed
sag_py_fastapi_health/checks/storage.py
sag_py_fastapi_health-0.3.3.dist-info/licenses/LICENSE.txt
sag_py_fastapi_health-0.3.3.dist-info/METADATA
sag_py_fastapi_health-0.3.3.dist-info/WHEEL
sag_py_fastapi_health-0.3.3.dist-info/top_level.txt
sag_py_fastapi_health-0.3.3.dist-info/RECORD
