Metadata-Version: 2.4
Name: sag-py-fastapi-health
Version: 0.3.3
Summary: A library for fastapi health checks
Home-page: https://github.com/SamhammerAG/sag_py_fastapi_health
Author: Samhammer AG
Author-email: support@samhammer.de
License: MIT
Project-URL: Documentation, https://github.com/SamhammerAG/sag_py_fastapi_health
Project-URL: Bug Reports, https://github.com/SamhammerAG/sag_py_fastapi_health/issues
Project-URL: Source, https://github.com/SamhammerAG/sag_py_fastapi_health
Keywords: fastapi,health
Classifier: Programming Language :: Python :: 3
Classifier: License :: OSI Approved :: MIT License
Classifier: Operating System :: OS Independent
Classifier: Topic :: Software Development :: Libraries :: Python Modules
Classifier: Topic :: Software Development :: Libraries
Classifier: Topic :: Software Development
Requires-Python: >=3.12
License-File: LICENSE.txt
Requires-Dist: aiohttp[speedups]<4,>=3.9.4
Requires-Dist: fastapi<1,>=0.115.12
Requires-Dist: pydantic>=2.5.3
Requires-Dist: typing-extensions>=4.0.0
Requires-Dist: zipp>=3.21.0
Provides-Extra: dev
Requires-Dist: flake8; extra == "dev"
Requires-Dist: mypy; extra == "dev"
Requires-Dist: build; extra == "dev"
Requires-Dist: pytest; extra == "dev"
Requires-Dist: pytest-asyncio; extra == "dev"
Requires-Dist: pytest-cov; extra == "dev"
Requires-Dist: coverage-lcov; extra == "dev"
Requires-Dist: toml; extra == "dev"
Requires-Dist: coverage; extra == "dev"
Requires-Dist: mock; extra == "dev"
Requires-Dist: types-mock; extra == "dev"
Requires-Dist: zipp>=3.21.0; extra == "dev"
Dynamic: author
Dynamic: author-email
Dynamic: classifier
Dynamic: description
Dynamic: description-content-type
Dynamic: home-page
Dynamic: keywords
Dynamic: license
Dynamic: license-file
Dynamic: project-url
Dynamic: provides-extra
Dynamic: requires-dist
Dynamic: requires-python
Dynamic: summary
